farfarfun/__init__.py
farfarfun-202307211120.dist-info/METADATA
farfarfun-202307211120.dist-info/WHEEL
farfarfun-202307211120.dist-info/top_level.txt
farfarfun-202307211120.dist-info/RECORD
