Metadata-Version: 2.1
Name: farfarfun
Version: 202307211120
Summary: farfarfun
Home-page: https://github.com/1007530194
Author: bingtao
Author-email: 1007530194@qq.com
